[
    {   
        "id" : 1,
        "img": "https://dynamic-media-cdn.tripadvisor.com/media/photo-o/0f/ba/29/5c/img-worlds-of-adventure.jpg?w=1200&h=-1&s=1",
        "title": "YA NIKITA 2",
        "age": 20,
        "budget": 12000
    },
    {   
        "id" : 2,
        "img": "https://dynamic-media-cdn.tripadvisor.com/media/photo-o/0f/ba/29/5c/img-worlds-of-adventure.jpg?w=1200&h=-1&s=1",
        "age": 10,
        "title": "YA NIKITA 3",
        "budget": 22000
    },
    {   
        "id" : 2,
        "img": "https://dynamic-media-cdn.tripadvisor.com/media/photo-o/0f/ba/29/5c/img-worlds-of-adventure.jpg?w=1200&h=-1&s=1",
        "age": 22,
        "title": "YA NIKITA 3",
        "budget": 22000
    }
]